gendiscalpy/GenDisCal.py
gendiscalpy/GenDisCalTree.py
gendiscalpy/__init__.py
gendiscalpy/install_gendiscal.py
gendiscalpy/utils.py
gendiscalpy-0.0.2.dist-info/LICENCE.md
gendiscalpy-0.0.2.dist-info/METADATA
gendiscalpy-0.0.2.dist-info/WHEEL
gendiscalpy-0.0.2.dist-info/entry_points.txt
gendiscalpy-0.0.2.dist-info/top_level.txt
gendiscalpy-0.0.2.dist-info/RECORD
