Metadata-Version: 2.1
Name: gendiscalpy
Version: 0.0.2
Summary: Python bindings to GenDisCal and addition of phylogenetic tree function
Home-page: https://github.com/MrTomRod/gendiscalpy
Author: Thomas Roder
Author-email: roder.thomas@gmail.com
License: MIT
Classifier: License :: OSI Approved :: MIT License
Classifier: Programming Language :: Python :: 3
Classifier: Programming Language :: Python :: 3.10
License-File: LICENCE.md
Requires-Dist: fire
Requires-Dist: pandas
Requires-Dist: biotite
